UnCodeGL/__init__.py
UnCodeGL/code.py
UnCodeGL/source.py
UnCodeGL/data_structures/__init__.py
UnCodeGL/data_structures/encoder.py
UnCodeGL/data_structures/huffman_generator.py
UnCodeGL/data_structures/trie.py
UnCodeGL-0.0.6.dist-info/METADATA
UnCodeGL-0.0.6.dist-info/WHEEL
UnCodeGL-0.0.6.dist-info/top_level.txt
UnCodeGL-0.0.6.dist-info/RECORD
