Metadata-Version: 2.1
Name: UnCodeGL
Version: 0.0.6
Summary: Library for Coding Theory
Home-page: https://github.com/Matematikoi/UnCodeGL
Author: Gabriel Octavio Lozano Pinzon
Author-email: golozanop@unal.edu.co
License: UNKNOWN
Platform: UNKNOWN
Classifier: Programming Language :: Python :: 3
Classifier: License :: OSI Approved :: MIT License
Classifier: Operating System :: OS Independent
Requires-Python: >=3.6
